evals/__init__.py
evals/run_evals.py
openparse/__init__.py
openparse/_types.py
openparse/cli.py
openparse/config.py
openparse/consts.py
openparse/doc_parser.py
openparse/pdf.py
openparse/schemas.py
openparse/utils.py
openparse/version.py
openparse/processing/__init__.py
openparse/processing/basic_transforms.py
openparse/processing/ingest.py
openparse/processing/semantic_transforms.py
openparse/tables/__init__.py
openparse/tables/parse.py
openparse/tables/schemas.py
openparse/tables/utils.py
openparse/tables/pymupdf/__init__.py
openparse/tables/pymupdf/parse.py
openparse/tables/table_transformers/__init__.py
openparse/tables/table_transformers/geometry.py
openparse/tables/table_transformers/ml.py
openparse/tables/table_transformers/schemas.py
openparse/tables/unitable/__init__.py
openparse/tables/unitable/config.py
openparse/tables/unitable/core.py
openparse/tables/unitable/schemas.py
openparse/tables/unitable/tabular_transformer.py
openparse/tables/unitable/tokens.py
openparse/tables/unitable/unitable_model.py
openparse/tables/unitable/utils.py
openparse/text/__init__.py
openparse/text/parse.py
openparse/text/pdfminer/__init__.py
openparse/text/pdfminer/core.py
openparse/text/pymupdf/__init__.py
openparse/text/pymupdf/core.py
tests/__init__.py
tests/conftest.py
tests/test_doc_parser.py
tests/test_main.py
tests/test_schemas.py
tests/processing/__init__.py
tests/processing/test_pipeline.py
tests/processing/test_steps.py
tests/tables/__init__.py
tests/tables/pymupdf/__init__.py
tests/tables/pymupdf/test_parse.py
tests/tables/transformers/__init__.py
tests/tables/transformers/test_geometry.py
tests/tables/transformers/test_ml.py
tests/tables/unitable/__init__.py
tests/tables/unitable/sample_pred_outputs.py
tests/tables/unitable/test_pred_to_schema.py
tests/text/pdf_miner/test_core.py
openparse-0.7.0.dist-info/LICENSE
openparse-0.7.0.dist-info/METADATA
openparse-0.7.0.dist-info/WHEEL
openparse-0.7.0.dist-info/entry_points.txt
openparse-0.7.0.dist-info/top_level.txt
openparse-0.7.0.dist-info/RECORD
