Metadata-Version: 2.1
Name: openparse
Version: 0.7.0
Summary: Streamlines the process of preparing documents for LLM's.
Author-email: Sergey Filimonov <hello@sergey.fyi>
License: MIT
Project-URL: homepage, https://github.com/Filimoa/open-parse
Project-URL: repository, https://github.com/Filimoa/open-parse
Project-URL: documentation, https://filimoa.github.io/open-parse
Requires-Python: >=3.8
License-File: LICENSE
Requires-Dist: PyMuPDF>=1.23.2
Requires-Dist: pillow>=8.3
Requires-Dist: pydantic>=2.0
Requires-Dist: pypdf>=4.0.0
Requires-Dist: pdfminer.six>=20200401
Requires-Dist: tiktoken>=0.3
Requires-Dist: openai>=1.0.0
Requires-Dist: numpy
Provides-Extra: ml
Requires-Dist: torch; extra == "ml"
Requires-Dist: torchvision; extra == "ml"
Requires-Dist: transformers; extra == "ml"
Requires-Dist: tokenizers; extra == "ml"
